Metadata-Version: 2.1
Name: madx
Version: 0.0.1
Summary: Methodical Accelerator Design MAD-X
Home-page: https://github.com/MethodicalAcceleratorDesign/mad-x
Author: CERN
Author-email: riccardo.de.maria@cern.ch
